{"Align Telecopse": {"Laboratory": [33.781845, -5.952718]}, "Chart Course": {"Dropship": [15.991005, -0.75594616]}, "Clear Asteroids": {"Weapons": [10.344007, -23.126253]}, "Empty Garbage": {"Oxygen": [5.0592184, -21.23253]}, "Fill Canisters": {"Oxygen": [1.2051549, -20.051916]}, "Activate Weather Nodes": {"NODE_PD": [15.00621, -25.60051], "Laboratory": [29.489998, -7.325563], "NODE_MLG": [30.591537, -12.668413], "NODE_CA": [23.060648, -7.613561], "NODE_GI": [14.431117, -12.327277], "NODE_TB": [8.619246, -15.860107], "NODE_IRO": [7.186267, -25.516897]}, "Fix Wiring": {"Office": [16.401752, -19.088335], "Decontamination": [40.619236, -9.527025]}, "Fuel Engines": {}, "Insert Keys": {}, "Inspect Sample": {}, "Monitor Oxygen": {}, "Open Waterways": {}, "Reboot Wifi": {}, "Record Temperature": {}, "Repair Drill": {}, "Replace Water Jug": {}, "Scan Boarding Pass": {}, "Start Reactor": {}, "Store Artifacts": {}, "Submit Scan": {}, "Swipe Card": {}, "Unlock Manifolds": {}, "Upload Data": {}}